{
  "schemaVersion": 1,
  "id": "youtubers",
  "version": 1,
  "updatedAt": "2026-06-03T15:31:34.027512Z",
  "minOptions": 2,
  "names": {
    "vi": "YouTuber nổi tiếng",
    "en": "Youtubers",
    "ja": "人気YouTuber",
    "hi": "लोकप्रिय YouTuber",
    "it": "YouTuber famosi",
    "es": "YouTubers famosos",
    "fil": "Sikat na YouTuber",
    "pt": "YouTubers famosos",
    "th": "YouTuber ยอดนิยม"
  },
  "options": {
    "vi": [
      "MrBeast",
      "PewDiePie",
      "Markiplier",
      "Jacksepticeye",
      "Dude Perfect",
      "VanossGaming",
      "DanTDM",
      "SSSniperWolf",
      "Jelly",
      "Ali-A",
      "KSI",
      "Logan Paul",
      "Jake Paul",
      "Dream",
      "Technoblade",
      "Corpse Husband",
      "Valkyrae",
      "Pokimane",
      "xQc",
      "IShowSpeed",
      "Khaby Lame",
      "Charli D'Amelio",
      "MrBeast Gaming",
      "LazarBeam",
      "Sidemen",
      "Fernanfloo",
      "ElRubius",
      "Whindersson Nunes",
      "CarryMinati",
      "BB Ki Vines",
      "HikakinTV",
      "Hajime Syacho",
      "Kimberly Loaiza",
      "Like Nastya",
      "Cocomelon",
      "T-Series",
      "SET India",
      "Wired",
      "Linus Tech Tips",
      "MKBHD"
    ],
    "en": [
      "MrBeast",
      "PewDiePie",
      "Markiplier",
      "Jacksepticeye",
      "Dude Perfect",
      "VanossGaming",
      "DanTDM",
      "SSSniperWolf",
      "Jelly",
      "Ali-A",
      "KSI",
      "Logan Paul",
      "Jake Paul",
      "Dream",
      "Technoblade",
      "Corpse Husband",
      "Valkyrae",
      "Pokimane",
      "xQc",
      "IShowSpeed",
      "Khaby Lame",
      "Charli D'Amelio",
      "MrBeast Gaming",
      "LazarBeam",
      "Sidemen",
      "Fernanfloo",
      "ElRubius",
      "Whindersson Nunes",
      "CarryMinati",
      "BB Ki Vines",
      "HikakinTV",
      "Hajime Syacho",
      "Kimberly Loaiza",
      "Like Nastya",
      "Cocomelon",
      "T-Series",
      "SET India",
      "Wired",
      "Linus Tech Tips",
      "MKBHD"
    ],
    "ja": [
      "MrBeast",
      "PewDiePie",
      "Markiplier",
      "Jacksepticeye",
      "Dude Perfect",
      "VanossGaming",
      "DanTDM",
      "SSSniperWolf",
      "Jelly",
      "Ali-A",
      "KSI",
      "Logan Paul",
      "Jake Paul",
      "Dream",
      "Technoblade",
      "Corpse Husband",
      "Valkyrae",
      "Pokimane",
      "xQc",
      "IShowSpeed",
      "Khaby Lame",
      "Charli D'Amelio",
      "MrBeast Gaming",
      "LazarBeam",
      "Sidemen",
      "Fernanfloo",
      "ElRubius",
      "Whindersson Nunes",
      "CarryMinati",
      "BB Ki Vines",
      "HikakinTV",
      "Hajime Syacho",
      "Kimberly Loaiza",
      "Like Nastya",
      "Cocomelon",
      "T-Series",
      "SET India",
      "Wired",
      "Linus Tech Tips",
      "MKBHD"
    ],
    "hi": [
      "MrBeast",
      "PewDiePie",
      "Markiplier",
      "Jacksepticeye",
      "Dude Perfect",
      "VanossGaming",
      "DanTDM",
      "SSSniperWolf",
      "Jelly",
      "Ali-A",
      "KSI",
      "Logan Paul",
      "Jake Paul",
      "Dream",
      "Technoblade",
      "Corpse Husband",
      "Valkyrae",
      "Pokimane",
      "xQc",
      "IShowSpeed",
      "Khaby Lame",
      "Charli D'Amelio",
      "MrBeast Gaming",
      "LazarBeam",
      "Sidemen",
      "Fernanfloo",
      "ElRubius",
      "Whindersson Nunes",
      "CarryMinati",
      "BB Ki Vines",
      "HikakinTV",
      "Hajime Syacho",
      "Kimberly Loaiza",
      "Like Nastya",
      "Cocomelon",
      "T-Series",
      "SET India",
      "Wired",
      "Linus Tech Tips",
      "MKBHD"
    ],
    "it": [
      "MrBeast",
      "PewDiePie",
      "Markiplier",
      "Jacksepticeye",
      "Dude Perfect",
      "VanossGaming",
      "DanTDM",
      "SSSniperWolf",
      "Jelly",
      "Ali-A",
      "KSI",
      "Logan Paul",
      "Jake Paul",
      "Dream",
      "Technoblade",
      "Corpse Husband",
      "Valkyrae",
      "Pokimane",
      "xQc",
      "IShowSpeed",
      "Khaby Lame",
      "Charli D'Amelio",
      "MrBeast Gaming",
      "LazarBeam",
      "Sidemen",
      "Fernanfloo",
      "ElRubius",
      "Whindersson Nunes",
      "CarryMinati",
      "BB Ki Vines",
      "HikakinTV",
      "Hajime Syacho",
      "Kimberly Loaiza",
      "Like Nastya",
      "Cocomelon",
      "T-Series",
      "SET India",
      "Wired",
      "Linus Tech Tips",
      "MKBHD"
    ],
    "es": [
      "MrBeast",
      "PewDiePie",
      "Markiplier",
      "Jacksepticeye",
      "Dude Perfect",
      "VanossGaming",
      "DanTDM",
      "SSSniperWolf",
      "Jelly",
      "Ali-A",
      "KSI",
      "Logan Paul",
      "Jake Paul",
      "Dream",
      "Technoblade",
      "Corpse Husband",
      "Valkyrae",
      "Pokimane",
      "xQc",
      "IShowSpeed",
      "Khaby Lame",
      "Charli D'Amelio",
      "MrBeast Gaming",
      "LazarBeam",
      "Sidemen",
      "Fernanfloo",
      "ElRubius",
      "Whindersson Nunes",
      "CarryMinati",
      "BB Ki Vines",
      "HikakinTV",
      "Hajime Syacho",
      "Kimberly Loaiza",
      "Like Nastya",
      "Cocomelon",
      "T-Series",
      "SET India",
      "Wired",
      "Linus Tech Tips",
      "MKBHD"
    ],
    "fil": [
      "MrBeast",
      "PewDiePie",
      "Markiplier",
      "Jacksepticeye",
      "Dude Perfect",
      "VanossGaming",
      "DanTDM",
      "SSSniperWolf",
      "Jelly",
      "Ali-A",
      "KSI",
      "Logan Paul",
      "Jake Paul",
      "Dream",
      "Technoblade",
      "Corpse Husband",
      "Valkyrae",
      "Pokimane",
      "xQc",
      "IShowSpeed",
      "Khaby Lame",
      "Charli D'Amelio",
      "MrBeast Gaming",
      "LazarBeam",
      "Sidemen",
      "Fernanfloo",
      "ElRubius",
      "Whindersson Nunes",
      "CarryMinati",
      "BB Ki Vines",
      "HikakinTV",
      "Hajime Syacho",
      "Kimberly Loaiza",
      "Like Nastya",
      "Cocomelon",
      "T-Series",
      "SET India",
      "Wired",
      "Linus Tech Tips",
      "MKBHD"
    ],
    "pt": [
      "MrBeast",
      "PewDiePie",
      "Markiplier",
      "Jacksepticeye",
      "Dude Perfect",
      "VanossGaming",
      "DanTDM",
      "SSSniperWolf",
      "Jelly",
      "Ali-A",
      "KSI",
      "Logan Paul",
      "Jake Paul",
      "Dream",
      "Technoblade",
      "Corpse Husband",
      "Valkyrae",
      "Pokimane",
      "xQc",
      "IShowSpeed",
      "Khaby Lame",
      "Charli D'Amelio",
      "MrBeast Gaming",
      "LazarBeam",
      "Sidemen",
      "Fernanfloo",
      "ElRubius",
      "Whindersson Nunes",
      "CarryMinati",
      "BB Ki Vines",
      "HikakinTV",
      "Hajime Syacho",
      "Kimberly Loaiza",
      "Like Nastya",
      "Cocomelon",
      "T-Series",
      "SET India",
      "Wired",
      "Linus Tech Tips",
      "MKBHD"
    ],
    "th": [
      "MrBeast",
      "PewDiePie",
      "Markiplier",
      "Jacksepticeye",
      "Dude Perfect",
      "VanossGaming",
      "DanTDM",
      "SSSniperWolf",
      "Jelly",
      "Ali-A",
      "KSI",
      "Logan Paul",
      "Jake Paul",
      "Dream",
      "Technoblade",
      "Corpse Husband",
      "Valkyrae",
      "Pokimane",
      "xQc",
      "IShowSpeed",
      "Khaby Lame",
      "Charli D'Amelio",
      "MrBeast Gaming",
      "LazarBeam",
      "Sidemen",
      "Fernanfloo",
      "ElRubius",
      "Whindersson Nunes",
      "CarryMinati",
      "BB Ki Vines",
      "HikakinTV",
      "Hajime Syacho",
      "Kimberly Loaiza",
      "Like Nastya",
      "Cocomelon",
      "T-Series",
      "SET India",
      "Wired",
      "Linus Tech Tips",
      "MKBHD"
    ]
  }
}